__init__.py
fullapp/__init__.py
fullapp/apporm.py
fullapp/myapp.py
fullapp-0.0.5.dist-info/LICENSE
fullapp-0.0.5.dist-info/METADATA
fullapp-0.0.5.dist-info/WHEEL
fullapp-0.0.5.dist-info/top_level.txt
fullapp-0.0.5.dist-info/RECORD
