Metadata-Version: 2.1
Name: fullapp
Version: 0.0.5
Summary: fullapp TDB
Author-email: Graham Coster <bitjugglers@gmail.com>
Project-URL: Homepage, https://github.com/grumBit/fullapp.git
Project-URL: Bug Tracker, https://github.com/grumBit/fullapp/issues
Project-URL: Source, https://github.com/grumBit/fullapp
Project-URL: Security Policy, https://github.com/grumbit/fullapp/blob/master/.github/SECURITY.md
Classifier: Development Status :: 5 - Production/Stable
Classifier: Programming Language :: Python :: 3
Classifier: License :: OSI Approved :: MIT License
Classifier: Operating System :: OS Independent
Requires-Python: >=3.11
License-File: LICENSE
Requires-Dist: alembic (==1.10.4)
Requires-Dist: anyio (==3.6.2)
Requires-Dist: certifi (==2022.12.7)
Requires-Dist: click (==8.1.3)
Requires-Dist: dnspython (==2.3.0)
Requires-Dist: email-validator (==2.0.0.post2)
Requires-Dist: fastapi[all] (==0.95.1)
Requires-Dist: h11 (==0.14.0)
Requires-Dist: httpcore (==0.17.0)
Requires-Dist: httptools (==0.5.0)
Requires-Dist: httpx (==0.24.0)
Requires-Dist: idna (==3.4)
Requires-Dist: itsdangerous (==2.1.2)
Requires-Dist: jinja2 (==3.1.2)
Requires-Dist: mako (==1.2.4)
Requires-Dist: markupsafe (==2.1.2)
Requires-Dist: mypy (==1.2.0)
Requires-Dist: mypy-extensions (==1.0.0)
Requires-Dist: orjson (==3.8.11)
Requires-Dist: psycopg2 (==2.9.6)
Requires-Dist: pydantic (==1.10.7)
Requires-Dist: python-dotenv (==1.0.0)
Requires-Dist: python-multipart (==0.0.6)
Requires-Dist: pyyaml (==6.0)
Requires-Dist: sniffio (==1.3.0)
Requires-Dist: sqlalchemy[mypy] (==2.0.11)
Requires-Dist: starlette (==0.26.1)
Requires-Dist: typing-extensions (==4.5.0)
Requires-Dist: ujson (==5.7.0)
Requires-Dist: uvicorn[standard] (==0.22.0)
Requires-Dist: uvloop (==0.17.0)
Requires-Dist: watchfiles (==0.19.0)
Requires-Dist: websockets (==11.0.2)
